Metadata-Version: 1.0
Name: email_extractor
Version: v1
Summary: Extract Emails by using webcrawl Extract Url links from a site
Home-page: http://www.jaist.ac.jp/~s1010205/email_extractor/html/index.html
Author: KATHURIA Pulkit
Author-email: kevincobain2000@gmail.com
License: BSD
Keywords: http://www.jaist.ac.jp/~s1010205/email_extractor/html/index.html
Platform: UNKNOWN
Classifier: Development Status :: 6 - Mature
Classifier: Topic :: Utilities
